{
"camera":{"title":"The \"Camera\" and Geometric Transforms"},
"filters":{"title":"Graphics Filters"},
"glmath":{"title":"H3DU's Math Functions"},
"colors":{"title":"Color Strings"},
"matrixdetails":{"title":"Matrix Details"},
"overview":{"title":"Library Overview"},
"shapes":{"title":"Creating Shapes"},
"surfaces":{"title":"Parametric Curves and Parametric Surfaces"},
"subclass":{"title":"Subclassing"},
"paths":{"title":"2-Dimensional Graphics Paths"},
"textures":{"title":"Texture Examples"},
"meshexamples":{"title":"Examples of Creating Meshes on the Fly"},
"history":{"title":"Older Version History"}
}
